{
    "projects": [
        {
            "name": "Loom By Light",
            "description": "Arduino Application to assist with manual loom production of custom patterns.",
            "demo": null,
            "image": "/images/loom-by-light.jpg",
            "learnMore": {
                "name": "Loom by Light",
                "info": "Loom by Light was a freelance project commissioned by a textile artist. The Arduino application was designed to run on low spec Arduinos. It allos converting of bitmap images into rows of LED lights for weaving on a custom manual loom.",
                "links": [
                    {
                        "name": "GitHub",
                        "url": "https://github.com/tjjoris/loom_by_light"
                    }
                ]
            },
            "categories": [
                "Other"
            ]
        },
        {
            "name": "Fuzzy Kittens",
            "description": "Web forums for cat lovers. Built in PHP",
            "demo": null,
            "image": "/images/fuzzy-kittens-login.png",
            "learnMore": {
                "name": "Fuzzy Kittens",
                "info": "Fuzzy Kittens was a group project for Algonquin College Computer Programming. I was the group leader and developed all of the back end, enabling CRUD operations for a message board. The back end was written in PHP, the front-end was written in HTML, CSS, and JavaScript.",
                "links": [
                    {
                        "name": "GitHub",
                        "url": "https://github.com/tjjoris/L2-Web-Assignment2"
                    }
                ]
            },
            "categories": [
                "Back-end"
            ]
        },
        {
            "name": "Science of Realms",
            "description": "An award winning platformer game built in Godot and GDScript.",
            "demo": "https://tarsin.itch.io/scienceofrealms",
            "image": "/images/science-of-realms-cover-image2.png",
            "learnMore": {
                "name": "Science of Realms",
                "info": "Find your way home by teleporting between realms, but beware of traps and enemies. This Game Jam entry was developed in Godot by a team of 6 and won an award for its excellent artwork.",
                "links": [
                    {
                        "name": "GitHub",
                        "url": "https://github.com/tjjoris/DEP_GoedWareJam"
                    }
                ]
            },
            "categories": [
                "Top Games"
            ]
        },
        {
            "name": "User Catalogue",
            "description": "Program for creating, editing, and deleting user profiles. uses Laravel RESTful back-end API, and separate React front-end.",
            "demo": "https://demo2-front-end.luke-j.com/",
            "image": "/images/full-stack-REST.png",
            "learnMore": {
                "name": "User Catalogue",
                "info": "This Project has a separate back end and back end, allowing future deployment of front end on different platforms. The repository features user authentication utilizing both session based for the web based front end, and token based for RESTful API’s.",
                "links": [
                    {
                        "name": "GitHub Front End",
                        "url": "https://github.com/tjjoris/demo2-react-front-end"
                    },
                    {
                        "name": "GitHub Back End",
                        "url": "https://github.com/tjjoris/demo2-laravel-rest-back-end"
                    }
                ]
            },
            "categories": [
                "Front-end",
                "Back-end"
            ]
        },
        {
            "name": "Message Board",
            "description": "App allows users to post, edit, and delete messages. Uses Laravel and MySQL for back-end, with integrated React front-end.",
            "demo": "https://demo1.luke-j.com/",
            "image": "images/full-stack-inertia.png",
            "learnMore": {
                "name": "Message Board",
                "info": "This message board features user authentication for CRUD operations, including user ownership of posts.",
                "links": [
                    {
                        "name": "GitHub",
                        "url": "https://github.com/tjjoris/demo1-react-laravel"
                    }
                ]
            },
            "categories": [
                "Front-end",
                "Back-end"
            ]
        },
        {
            "name": "Otherworldly Relics",
            "description": "A puzzle based game built using Unity and C#.",
            "demo": "https://tarsin.itch.io/otherworldly-relics",
            "image": "/images/otherworldly-relics-get-em.png",
            "learnMore": {
                "name": "Otherworldly Relics",
                "info": "A Game Jam entry by a team of 3. A very short prototype of an in development hex tile puzzle game involving a devious occult plot, a gumshoe who will not put up with their shenanigans and multiple dimensions colliding in on itself!",
                "links": [
                    {
                        "name": "GitHub",
                        "url": "https://github.com/Tars1n/GameJam-2023April"
                    }
                ]
            },
            "categories": [
                "Top Games"
            ]
        },
        {
            "name": "Loop Destroyer",
            "description": "A clicker game built in React and TypeScript.",
            "demo": "https://tjjoris.itch.io/loop-destroyer",
            "image": "/images/Loop-destroyer.png",
            "learnMore": {
                "name": "Loop Destroyer",
                "info": "A Game Jam entry by a team of 3. Click the ball of elastics to break loops and gain points.  Buy upgrades for automatic loop breaking.  Higher tier upgrades break more loops per second but cost more.",
                "links": [
                    {
                        "name": "GitHub",
                        "url": "https://github.com/tjjoris/Loop_Clicker"
                    }
                ]
            },
            "categories": [
                "Top Games",
                "Front-end"
            ]
        },
        {
            "name": "Spacelane Sweeper",
            "description": "Clear the space lanes of debris in this 2D newtonian space sim, developed in Unity and C#.",
            "demo": "https://tarsin.itch.io/spacelane-sweeper",
            "image": "images/space-lane-sweeper-cover-image.png",
            "learnMore": {
                "name": "Spacelane Sweeper",
                "info": "This Game Jam entry features multiple tools for destroying debris, and a complex physics system.",
                "links": [
                    {
                        "name": "GitHub",
                        "url": ""
                    }
                ]
            },
            "categories": [
                "Top Games"
            ]
        },
        {
            "name": "",
            "description": "",
            "demo": "",
            "image": "/images/",
            "learnMore": {
                "name": "",
                "info": "",
                "links": [
                    {
                        "name": "GitHub",
                        "url": ""
                    }
                ]
            },
            "categories": [
                ""
            ]
        },
        {
            "name": "Route Finder",
            "description": "Web app for finding routes between two locations, and storing them in a database to minimize google maps API calls. Back-end built in PHP and MongoDB.",
            "demo": "",
            "image": "images/one-stop-transpo.png",
            "learnMore": {
                "name": "Route Finder",
                "info": "This was a group project for Algonquin College Computer Programming. I was in charge of developing the back-end business logic in PHP, including google maps API calls.  The front-end was developed in HTML, CSS, and JavaScript.",
                "links": []
            },
            "categories": [
                "Back-end"
            ]
        },
        {
            "name": "Perscription Management Tool",
            "description": "A Jakarta EE program that handles back-end CRUD RESTful API requests for prescription management.",
            "demo": "",
            "image": "images/Jakarta-EE-icon.png",
            "learnMore": {
                "name": "Perscription Management Tool",
                "info": "This was a group project for Algonquin College Computer Programming, my role was debugging the back end RESTful API calls.",
                "links": []
            },
            "categories": [
                "Back-end"
            ]
        },
        {
            "name": "",
            "description": "",
            "demo": "",
            "image": "/images/",
            "learnMore": {
                "name": "",
                "info": "",
                "links": [
                    {
                        "name": "GitHub",
                        "url": ""
                    }
                ]
            },
            "categories": [
                ""
            ]
        },
        {
            "name": "",
            "description": "",
            "demo": "",
            "image": "/images/",
            "learnMore": {
                "name": "",
                "info": "",
                "links": [
                    {
                        "name": "GitHub",
                        "url": ""
                    }
                ]
            },
            "categories": [
                ""
            ]
        },
        {
            "name": "",
            "description": "",
            "demo": "",
            "image": "/images/",
            "learnMore": {
                "name": "",
                "info": "",
                "links": [
                    {
                        "name": "GitHub",
                        "url": ""
                    }
                ]
            },
            "categories": [
                ""
            ]
        },
        {
            "name": "",
            "description": "",
            "demo": "",
            "image": "/images/",
            "learnMore": {
                "name": "",
                "info": "",
                "links": [
                    {
                        "name": "GitHub",
                        "url": ""
                    }
                ]
            },
            "categories": [
                ""
            ]
        },
        {
            "name": "",
            "description": "",
            "demo": "",
            "image": "/images/",
            "learnMore": {
                "name": "",
                "info": "",
                "links": [
                    {
                        "name": "GitHub",
                        "url": ""
                    }
                ]
            },
            "categories": [
                ""
            ]
        }
    ]
}